EIS_Fitting_Yang/EIS_Fitting_Yang.py
EIS_Fitting_Yang/__init__.py
EIS_Fitting_Yang-0.0.9.dist-info/LICENSE
EIS_Fitting_Yang-0.0.9.dist-info/METADATA
EIS_Fitting_Yang-0.0.9.dist-info/WHEEL
EIS_Fitting_Yang-0.0.9.dist-info/top_level.txt
EIS_Fitting_Yang-0.0.9.dist-info/RECORD
