Metadata-Version: 2.1
Name: EIS-Fitting-Yang
Version: 0.0.9
Summary: CNLS fitting for EIS spectra
Home-page: 
Author: Tianrang Yang
Author-email: tianrangyang@gmail.com
License: UNKNOWN
Platform: UNKNOWN
Classifier: Programming Language :: Python :: 3
Classifier: License :: OSI Approved :: MIT License
Classifier: Operating System :: OS Independent
Requires-Python: >=3.6
Requires-Dist: numpy
Requires-Dist: pandas
Requires-Dist: mpmath
Requires-Dist: matplotlib
Requires-Dist: lmfit
